delt/__init__.py
delt/admin.py
delt/apps.py
delt/bridge/__init__.py
delt/bridge/arkitekt.py
delt/bridge/auth.py
delt/bridge/base.py
delt/discover.py
delt/initialize.py
delt/management/__init__.py
delt/management/commands/__init__.py
delt/management/commands/register_nodes.py
delt/management/commands/register_point.py
delt/messages/__init__.py
delt/messages/base.py
delt/messages/exception.py
delt/messages/generics.py
delt/messages/host/__init__.py
delt/messages/host/activate_pod.py
delt/messages/host/deactivate_pod.py
delt/messages/postman/__init__.py
delt/messages/postman/assign/__init__.py
delt/messages/postman/assign/assign.py
delt/messages/postman/assign/assign_critical.py
delt/messages/postman/assign/assign_done.py
delt/messages/postman/assign/assign_progress.py
delt/messages/postman/assign/assign_return.py
delt/messages/postman/assign/assign_yield.py
delt/messages/postman/assign/bounced_assign.py
delt/messages/postman/assign/bounced_forwarded_assign.py
delt/messages/postman/exception.py
delt/messages/postman/progress.py
delt/messages/postman/provide/__init__.py
delt/messages/postman/provide/bounced_provide.py
delt/messages/postman/provide/params.py
delt/messages/postman/provide/provide.py
delt/messages/postman/provide/provide_critical.py
delt/messages/postman/provide/provide_done.py
delt/messages/postman/provide/provide_progress.py
delt/messages/postman/reserve/__init__.py
delt/messages/postman/reserve/bounced_forwarded_reserve.py
delt/messages/postman/reserve/bounced_reserve.py
delt/messages/postman/reserve/params.py
delt/messages/postman/reserve/reserve.py
delt/messages/postman/reserve/reserve_critical.py
delt/messages/postman/reserve/reserve_done.py
delt/messages/postman/reserve/reserve_progress.py
delt/messages/postman/unassign/__init__.py
delt/messages/postman/unassign/bounced_unassign.py
delt/messages/postman/unassign/unassign.py
delt/messages/postman/unassign/unassign_critical.py
delt/messages/postman/unassign/unassign_done.py
delt-0.1.12.dist-info/WHEEL
delt-0.1.12.dist-info/METADATA
delt-0.1.12.dist-info/RECORD
